MANIFEST.in
README.txt
setup.cfg
setup.py
zgeo/__init__.py
zgeo.wfs.egg-info/PKG-INFO
zgeo.wfs.egg-info/SOURCES.txt
zgeo.wfs.egg-info/dependency_links.txt
zgeo.wfs.egg-info/entry_points.txt
zgeo.wfs.egg-info/namespace_packages.txt
zgeo.wfs.egg-info/not-zip-safe
zgeo.wfs.egg-info/requires.txt
zgeo.wfs.egg-info/top_level.txt
zgeo/wfs/README.txt
zgeo/wfs/__init__.py
zgeo/wfs/configure.zcml
zgeo/wfs/debug.txt
zgeo/wfs/events.py
zgeo/wfs/geoitem.py
zgeo/wfs/geoitem.txt
zgeo/wfs/interfaces.py
zgeo/wfs/license.txt
zgeo/wfs/webfeatureservice.py
zgeo/wfs/webfeatureservice.txt
zgeo/wfs/zope2.py
zgeo/wfs/browser/__init__.py
zgeo/wfs/browser/editFeatureTypes.pt
zgeo/wfs/browser/editGeometry.pt
zgeo/wfs/browser/error.xml
zgeo/wfs/browser/geoitemview.py
zgeo/wfs/browser/wfs.py
zgeo/wfs/browser/wfs_capabilities.xml
zgeo/wfs/browser/wfs_feature.xml
zgeo/wfs/browser/wfs_featuretype.xml
zgeo/wfs/geocatalog/__init__.py
zgeo/wfs/geocatalog/catalog.py
zgeo/wfs/geocatalog/geofeatureindex.py
zgeo/wfs/geocatalog/geometryindex.py
zgeo/wfs/geocatalog/index.py
zgeo/wfs/geocatalog/rtree.txt
zgeo/wfs/tests/__init__.py
zgeo/wfs/tests/debug.txt
zgeo/wfs/tests/geoitem.txt
zgeo/wfs/tests/tests.py
zgeo/wfs/tests/tests_unit.py
zgeo/wfs/tests/unit.txt
zgeo/wfs/tests/webfeatureservice.txt