Metadata-Version: 1.0
Name: zgeo.wfs
Version: 0.2.1
Summary: WFS server implementation for Zope
Home-page: http://trac.gispython.org/primagis/wiki/zgeo.wfs
Author: Eric BREHAULT
Author-email: eric.brehault@makina-corpus.org
License: BSD
Keywords: gis geography wfs
Platform: UNKNOWN
Classifier: Programming Language :: Python
Classifier: Topic :: Software Development :: Libraries :: Python Modules
